AUTHORS
LICENSE
MANIFEST.in
VERSION
requirements.txt
setup.py
dict.sorted.egg-info/PKG-INFO
dict.sorted.egg-info/SOURCES.txt
dict.sorted.egg-info/dependency_links.txt
dict.sorted.egg-info/requires.txt
dict.sorted.egg-info/top_level.txt
docs/Makefile
docs/conf.py
docs/index.rst
docs/_build/doctrees/environment.pickle
docs/_build/doctrees/index.doctree
docs/_build/html/.buildinfo
docs/_build/html/genindex.html
docs/_build/html/index.html
docs/_build/html/objects.inv
docs/_build/html/search.html
docs/_build/html/searchindex.js
docs/_build/html/_sources/index.txt
docs/_build/html/_static/ajax-loader.gif
docs/_build/html/_static/basic.css
docs/_build/html/_static/comment-bright.png
docs/_build/html/_static/comment-close.png
docs/_build/html/_static/comment.png
docs/_build/html/_static/default.css
docs/_build/html/_static/dialog-note.png
docs/_build/html/_static/dialog-seealso.png
docs/_build/html/_static/dialog-todo.png
docs/_build/html/_static/dialog-topic.png
docs/_build/html/_static/dialog-warning.png
docs/_build/html/_static/doctools.js
docs/_build/html/_static/down-pressed.png
docs/_build/html/_static/down.png
docs/_build/html/_static/epub.css
docs/_build/html/_static/file.png
docs/_build/html/_static/footerbg.png
docs/_build/html/_static/headerbg.png
docs/_build/html/_static/ie6.css
docs/_build/html/_static/jquery.js
docs/_build/html/_static/middlebg.png
docs/_build/html/_static/minus.png
docs/_build/html/_static/plus.png
docs/_build/html/_static/pygments.css
docs/_build/html/_static/pyramid.css
docs/_build/html/_static/searchtools.js
docs/_build/html/_static/sidebar.js
docs/_build/html/_static/transparent.gif
docs/_build/html/_static/underscore.js
docs/_build/html/_static/up-pressed.png
docs/_build/html/_static/up.png
docs/_build/html/_static/websupport.js
sdict/VERSION
sdict/__init__.py
sdict/alpha.py
sdict/base.py
sdict/utils.py